mannou/__init__.py
mannou/__main__.py
mannou/anilist.py
mannou/api.py
mannou/cli.py
mannou/exception.py
mannou/mannou.py
mannou/parser.py
mannou/util.py
mannou/site/__init__.py
mannou/site/komikid.py
mannou/site/manganelo.py
mannou-0.1.1.dist-info/AUTHORS.rst
mannou-0.1.1.dist-info/LICENSE
mannou-0.1.1.dist-info/METADATA
mannou-0.1.1.dist-info/WHEEL
mannou-0.1.1.dist-info/entry_points.txt
mannou-0.1.1.dist-info/top_level.txt
mannou-0.1.1.dist-info/RECORD
