Metadata-Version: 2.1
Name: mannou
Version: 0.1.1
Summary: A manga downloader from various sites.
Home-page: https://github.com/borderlineargs/mannou
Author: Muhammad Adi Prasojo
Author-email: borderlineargs@gmail.com
License: GNU General Public License v3
Keywords: mannou
Platform: UNKNOWN
Classifier: Development Status :: 2 - Pre-Alpha
Classifier: Intended Audience :: Developers
Classifier: License :: OSI Approved :: GNU General Public License v3 (GPLv3)
Classifier: Natural Language :: English
Classifier: Programming Language :: Python :: 3.6
Classifier: Programming Language :: Python :: 3.7
Requires-Dist: requests (>=2.19.0)
Requires-Dist: beautifulsoup4 (>=4.6.0)
Requires-Dist: tqdm (>=4.26.0)
